fastlogranktest/__init__.py
fastlogranktest/fastlogranktest.cp37-win_amd64.pyd
fastlogranktest/fastlogranktest.cpp
fastlogranktest/fastlogranktest.pyx
fastlogranktest/logrank_python.cpp
fastlogranktest/logrank_python.pxd
fastlogranktest-0.2.0.dist-info/AUTHORS.rst
fastlogranktest-0.2.0.dist-info/LICENSE
fastlogranktest-0.2.0.dist-info/METADATA
fastlogranktest-0.2.0.dist-info/WHEEL
fastlogranktest-0.2.0.dist-info/top_level.txt
fastlogranktest-0.2.0.dist-info/RECORD
