Metadata-Version: 2.1
Name: fastlogranktest
Version: 0.2.0
Summary: Perform the Log-Rank-Test very fast
Home-page: https://github.com/compsysmed/fastlogranktest.git
Author: Andreas Stelzer, Manuela Lautizi, Tim Kacprowski, Research group of computational systems medicine Chair of Experimental Bioinformatics TU Munich
Author-email: ga63nep@mytum.de, manuela.lautizi@wzw.tum.de, tim.kacprowski@wzw.tum.de
License: BSD
Keywords: fastlogranktest
Platform: UNKNOWN
Classifier: Development Status :: 2 - Pre-Alpha
Classifier: Intended Audience :: Developers
Classifier: License :: OSI Approved :: BSD License
Classifier: Natural Language :: English
Classifier: Programming Language :: Cython
Classifier: Programming Language :: Python :: 2
Classifier: Programming Language :: Python :: 2.7
Classifier: Programming Language :: Python :: 3
Classifier: Programming Language :: Python :: 3.4
Requires-Dist: cython
Requires-Dist: numpy
